{
  "explicit": [
    {"gua": "乾天上坤地下 · 三爻争锋", "route": "火路", "strategy": "压策", "source": "#528 明示"},
    {"gua": "震雷上艮山下 · 五爻乘时", "route": "火路", "strategy": "势策", "source": "#529 明示"},
    {"gua": "巽风上坤地下 · 二爻守中", "route": "冰路", "strategy": "稳策", "source": "#530 明示"},
    {"gua": "乾天上巽风下 · 三爻争锋", "route": "火路", "strategy": "压策", "source": "#531 明示"},
    {"gua": "兑泽上坎水下 · 初爻潜机", "route": "冰路", "strategy": "势策", "source": "#532 明示"},
    {"gua": "离火上艮山下 · 四爻转阵", "route": "冰路", "strategy": "稳策", "source": "#533 明示"},
    {"gua": "震雷上乾天下 · 上爻游变", "route": "火路", "strategy": "势策", "source": "#534 明示"},
    {"gua": "巽风上乾天下 · 二爻守中", "route": "火路", "strategy": "势策", "source": "#535 明示"},
    {"gua": "坎水上兑泽下 · 上爻游变", "route": "冰路", "strategy": "势策", "source": "#536 明示"},
    {"gua": "艮山上离火下 · 三爻争锋", "route": "火路", "strategy": "压策", "source": "#537 明示"},
    {"gua": "坤地上离火下 · 初爻潜机", "route": "冰路", "strategy": "稳策", "source": "#538 明示"},
    {"gua": "乾天上震雷下 · 二爻守中", "route": "火路", "strategy": "压策", "source": "#539 明示"},
    {"gua": "兑泽上巽风下 · 初爻潜机", "route": "冰路", "strategy": "势策", "source": "#540 明示"},
    {"gua": "离火上巽风下 · 三爻争锋", "route": "火路", "strategy": "压策", "source": "#541 明示"},
    {"gua": "震雷上巽风下 · 三爻争锋", "route": "火路", "strategy": "势策", "source": "#542 明示"},
    {"gua": "乾天上离火下 · 五爻乘时", "route": "火路", "strategy": "压策", "source": "#544 明示"},
    {"gua": "坎水上坤地下 · 上爻游变", "route": "冰路", "strategy": "稳策", "source": "#546 明示"},
    {"gua": "艮山上坤地下 · 三爻争锋", "route": "冰路", "strategy": "稳策", "source": "#547 明示"},
    {"gua": "坤地上坤地下 · 二爻守中", "route": "冰路", "strategy": "稳策", "source": "#548 明示"},
    {"gua": "乾天上乾天下 · 初爻潜机", "route": "火路", "strategy": "压策", "source": "#549 明示"},
    {"gua": "兑泽上乾天下 · 三爻争锋", "route": "火路", "strategy": "压策", "source": "#550 明示"},
    {"gua": "离火上离火下 · 初爻潜机", "route": "火路", "strategy": "压策", "source": "#551 明示"},
    {"gua": "巽风上坎水下 · 上爻游变", "route": "火路", "strategy": "势策", "source": "#552 明示"},
    {"gua": "坎水上巽风下 · 五爻乘时", "route": "火路", "strategy": "稳策", "source": "#553 明示"},
    {"gua": "坤地上兑泽下 · 初爻潜机", "route": "冰路", "strategy": "势策", "source": "#554 明示"}
  ],
  "success": [
    {"gua": "乾天上坤地下 · 上爻游变", "examples": [{"route": "火路", "strategy": "稳策", "source": "#561 顺"}, {"route": "火路", "strategy": "势策", "source": "#619 顺"}]},
    {"gua": "坎水上兑泽下 · 二爻守中", "examples": [{"route": "冰路", "strategy": "势策", "source": "#566 顺"}]},
    {"gua": "离火上震雷下 · 二爻守中", "examples": [{"route": "火路", "strategy": "稳策", "source": "#578 顺"}]},
    {"gua": "离火上乾天下 · 二爻守中", "examples": [{"route": "火路", "strategy": "稳策", "source": "#606 顺"}]},
    {"gua": "坎水上坤地下 · 二爻守中", "examples": [{"route": "冰路", "strategy": "势策", "source": "#608 顺"}, {"route": "冰路", "strategy": "稳策", "source": "#628 顺"}]},
    {"gua": "兑泽上艮山下 · 三爻争锋", "examples": [{"route": "冰路", "strategy": "压策", "source": "#627 顺"}]},
    {"gua": "兑泽上坎水下 · 三爻争锋", "examples": [{"route": "冰路", "strategy": "压策", "source": "#640 顺"}]},
    {"gua": "震雷上兑泽下 · 初爻潜机", "examples": [{"route": "冰路", "strategy": "稳策", "source": "#642 顺"}]},
    {"gua": "艮山上巽风下 · 初爻潜机", "examples": [{"route": "冰路", "strategy": "稳策", "source": "#657 顺"}]},
    {"gua": "兑泽上离火下 · 四爻转阵", "examples": [{"route": "冰路", "strategy": "稳策", "source": "#659 顺"}]}
  ],
  "failure": [
    {"gua": "乾天上巽风下 · 上爻游变", "examples": [{"route": "冰路", "strategy": "势策", "source": "#576 逆"}]},
    {"gua": "乾天上巽风下 · 四爻转阵", "examples": [{"route": "冰路", "strategy": "稳策", "source": "#662 逆"}]},
    {"gua": "震雷上艮山下 · 四爻转阵", "examples": [{"route": "火路", "strategy": "稳策", "source": "#579 逆"}]},
    {"gua": "艮山上震雷下 · 四爻转阵", "examples": [{"route": "火路", "strategy": "势策", "source": "#581 逆"}]},
    {"gua": "离火上离火下 · 三爻争锋", "examples": [{"route": "冰路", "strategy": "稳策", "source": "#620 逆"}]},
    {"gua": "离火上离火下 · 四爻转阵", "examples": [{"route": "冰路", "strategy": "势策", "source": "#629 逆"}]},
    {"gua": "震雷上坤地下 · 三爻争锋", "examples": [{"route": "冰路", "strategy": "势策", "source": "#630 逆"}]},
    {"gua": "乾天上艮山下 · 五爻乘时", "examples": [{"route": "冰路", "strategy": "势策", "source": "#632 逆"}]},
    {"gua": "离火上震雷下 · 四爻转阵", "examples": [{"route": "冰路", "strategy": "稳策", "source": "#633 逆"}]},
    {"gua": "兑泽上震雷下 · 三爻争锋", "examples": [{"route": "冰路", "strategy": "势策", "source": "#635 逆"}]},
    {"gua": "震雷上坤地下 · 二爻守中", "examples": [{"route": "火路", "strategy": "稳策", "source": "#648 逆"}]},
    {"gua": "乾天上离火下 · 三爻争锋", "examples": [{"route": "冰路", "strategy": "压策", "source": "#651 逆"}]},
    {"gua": "兑泽上坎水下 · 初爻潜机", "examples": [{"route": "火路", "strategy": "势策", "source": "#654 逆"}]}
  ]
}
